omc3_gui/__init__.py
omc3_gui/__main__.py
omc3_gui/sbs_gui.py
omc3_gui/plotting/classes.py
omc3_gui/plotting/element_lines.py
omc3_gui/plotting/latex_to_html.py
omc3_gui/plotting/tfs_plotter.py
omc3_gui/segment_by_segment/__init__.py
omc3_gui/segment_by_segment/defaults.py
omc3_gui/segment_by_segment/help_view.py
omc3_gui/segment_by_segment/main_controller.py
omc3_gui/segment_by_segment/main_model.py
omc3_gui/segment_by_segment/main_view.py
omc3_gui/segment_by_segment/measurement_model.py
omc3_gui/segment_by_segment/measurement_view.py
omc3_gui/segment_by_segment/plotting.py
omc3_gui/segment_by_segment/segment_model.py
omc3_gui/segment_by_segment/segment_view.py
omc3_gui/segment_by_segment/settings.py
omc3_gui/ui_components/__init__.py
omc3_gui/ui_components/base_classes_cvm.py
omc3_gui/ui_components/colors.py
omc3_gui/ui_components/file_dialogs.py
omc3_gui/ui_components/item_models.py
omc3_gui/ui_components/message_boxes.py
omc3_gui/ui_components/styles.py
omc3_gui/ui_components/text_editor.py
omc3_gui/ui_components/threads.py
omc3_gui/ui_components/widgets.py
omc3_gui/ui_components/dataclass_ui/__init__.py
omc3_gui/ui_components/dataclass_ui/controller.py
omc3_gui/ui_components/dataclass_ui/model.py
omc3_gui/ui_components/dataclass_ui/tools.py
omc3_gui/ui_components/dataclass_ui/view.py
omc3_gui/utils/__init__.py
omc3_gui/utils/counter.py
omc3_gui/utils/iteration_classes.py
omc3_gui/utils/log_handler.py
omc3_gui-1.0.1.dist-info/METADATA
omc3_gui-1.0.1.dist-info/WHEEL
omc3_gui-1.0.1.dist-info/licenses/LICENSE
omc3_gui-1.0.1.dist-info/RECORD
