Metadata-Version: 2.4
Name: omc3-gui
Version: 1.0.1
Summary: QT Graphical User Interface wrapper of the ``omc3`` package
Project-URL: homepage, https://github.com/pylhc/omc3_gui
Project-URL: repository, https://github.com/pylhc/omc3_gui
Project-URL: documentation, https://pylhc.github.io/omc3_gui/
Project-URL: changelog, https://github.com/pylhc/omc3_gui/blob/master/CHANGELOG.md
Author-email: OMC Team <pylhc@github.com>
License-Expression: MIT
License-File: LICENSE
Classifier: Intended Audience :: Science/Research
Classifier: License :: OSI Approved :: MIT License
Classifier: Natural Language :: English
Classifier: Operating System :: OS Independent
Classifier: Programming Language :: Python :: 3 :: Only
Classifier: Programming Language :: Python :: 3.10
Classifier: Programming Language :: Python :: 3.11
Classifier: Programming Language :: Python :: 3.12
Classifier: Programming Language :: Python :: 3.13
Classifier: Programming Language :: Python :: Implementation :: CPython
Classifier: Topic :: Scientific/Engineering
Classifier: Topic :: Scientific/Engineering :: Physics
Classifier: Topic :: Scientific/Engineering :: Visualization
Classifier: Topic :: Software Development :: Libraries :: Python Modules
Classifier: Typing :: Typed
Requires-Python: >=3.10
Requires-Dist: omc3>=0.24.0
Requires-Dist: pyqtgraph
Requires-Dist: qtpy>=2.3.1
Provides-Extra: all
Requires-Dist: accwidgets[app-frame,log-console]>=3.0.11; extra == 'all'
Requires-Dist: omc3[cern]; extra == 'all'
Requires-Dist: pytest-cov>=2.9; extra == 'all'
Requires-Dist: pytest-timeout>=1.4; extra == 'all'
Requires-Dist: pytest>=7.0; extra == 'all'
Requires-Dist: sphinx-rtd-theme>=2.0; extra == 'all'
Requires-Dist: sphinx>=7.0; extra == 'all'
Provides-Extra: cern
Requires-Dist: accwidgets[app-frame,log-console]>=3.0.11; extra == 'cern'
Requires-Dist: omc3[cern]; extra == 'cern'
Provides-Extra: doc
Requires-Dist: sphinx-rtd-theme>=2.0; extra == 'doc'
Requires-Dist: sphinx>=7.0; extra == 'doc'
Provides-Extra: test
Requires-Dist: pytest-cov>=2.9; extra == 'test'
Requires-Dist: pytest-timeout>=1.4; extra == 'test'
Requires-Dist: pytest>=7.0; extra == 'test'
